bulrush/__init__.py
bulrush/image_extractor.py
bulrush/license_generator.py
bulrush/schema_generator.py
bulrush/static/css/main.css
bulrush/templates/analytics.html
bulrush/templates/archives.html
bulrush/templates/article.html
bulrush/templates/article_infos.html
bulrush/templates/article_list.html
bulrush/templates/base.html
bulrush/templates/category.html
bulrush/templates/comments.html
bulrush/templates/disqus_script.html
bulrush/templates/github.html
bulrush/templates/index.html
bulrush/templates/mailchimp.html
bulrush/templates/mermaid.html
bulrush/templates/meta_tags.html
bulrush/templates/page.html
bulrush/templates/pagination.html
bulrush/templates/period_archives.html
bulrush/templates/social.html
bulrush/templates/tag.html
bulrush/templates/taglist.html
bulrush/templates/tags.html
bulrush/templates/translations.html
bulrush-0.6.3.dist-info/LICENSE
bulrush-0.6.3.dist-info/METADATA
bulrush-0.6.3.dist-info/WHEEL
bulrush-0.6.3.dist-info/top_level.txt
bulrush-0.6.3.dist-info/RECORD
