Metadata-Version: 2.1
Name: bulrush
Version: 0.6.3
Summary: Bulrush theme for Pelican
Home-page: https://github.com/textbook/bulrush
Author: Jonathan Sharpe
Author-email: mail@jonrshar.pe
License: ISC
Classifier: Development Status :: 4 - Beta
Classifier: Framework :: Pelican :: Themes
Classifier: License :: OSI Approved :: ISC License (ISCL)
Classifier: Programming Language :: Python :: 3 :: Only
License-File: LICENSE
Requires-Dist: markupsafe
Requires-Dist: webassets
